{
  "id": "MGI_MGI_1330290",
  "iri": "http://model.geneontology.org/MGI_MGI_1330290",
  "ttl_path": "models/MGI_MGI_1330290.ttl",
  "master_sha": "6a58093f893945d7b084fc8366587fd8596d7cb4",
  "generated_at": "2026-05-07T15:05:09.385Z",
  "metadata": {
    "title": "Ovol1 (MGI:MGI:1330290)",
    "modelstate": "production",
    "deprecated": false,
    "date": "2018-10-19",
    "contributors": [
      {
        "orcid": "https://orcid.org/0000-0001-7476-6306"
      },
      {
        "orcid": "https://orcid.org/0000-0002-2246-3722"
      }
    ],
    "providers": [
      {
        "iri": "http://informatics.jax.org"
      }
    ],
    "taxon": null,
    "taxon_label": null
  },
  "checks": [
    {
      "id": "rdf_valid",
      "kind": "rdf_valid",
      "label": "RDF Validity",
      "severity": "warning",
      "status": "pass",
      "ran_at": "2026-05-07T04:25:48.132Z",
      "violations": [],
      "last_passed_commit": "6a58093f893945d7b084fc8366587fd8596d7cb4",
      "last_passed_date": "2026-05-07T15:05:09.385Z"
    },
    {
      "id": "owl_consistency",
      "kind": "owl_consistency",
      "label": "OWL Consistency",
      "severity": "error",
      "status": "pass",
      "ran_at": "2026-05-07T04:25:48.132Z",
      "violations": [],
      "last_passed_commit": "6a58093f893945d7b084fc8366587fd8596d7cb4",
      "last_passed_date": "2026-05-07T15:05:09.385Z"
    },
    {
      "id": "gpad_compatibility",
      "kind": "gpad_compatibility",
      "label": "GPAD Compatibility",
      "severity": "info",
      "pass_label": "GPAD-compatible",
      "fail_label": "Causal model",
      "unknown_label": "Unknown shape",
      "status": "fail",
      "ran_at": "2026-05-07T04:25:48.132Z",
      "violations": [
        {
          "kind": "shex_nonconformant",
          "node": "",
          "shape": "http://purl.obolibrary.org/obo/go/shapes/Individual",
          "reason": "OR expression not satisfied:"
        },
        {
          "kind": "shex_nonconformant",
          "node": "",
          "shape": "http://purl.obolibrary.org/obo/go/shapes/Individual",
          "reason": "OR expression not satisfied:"
        },
        {
          "kind": "shex_nonconformant",
          "node": "",
          "shape": "http://purl.obolibrary.org/obo/go/shapes/Individual",
          "reason": "OR expression not satisfied:"
        },
        {
          "kind": "shex_nonconformant",
          "node": "",
          "shape": "http://purl.obolibrary.org/obo/go/shapes/Individual",
          "reason": "OR expression not satisfied:"
        },
        {
          "kind": "shex_nonconformant",
          "node": "",
          "shape": "http://purl.obolibrary.org/obo/go/shapes/Individual",
          "reason": "OR expression not satisfied:"
        },
        {
          "kind": "shex_nonconformant",
          "node": "",
          "shape": "http://purl.obolibrary.org/obo/go/shapes/Individual",
          "reason": "OR expression not satisfied:"
        },
        {
          "kind": "shex_nonconformant",
          "node": "",
          "shape": "http://purl.obolibrary.org/obo/go/shapes/Individual",
          "reason": "OR expression not satisfied:"
        },
        {
          "kind": "shex_nonconformant",
          "node": "",
          "shape": "http://purl.obolibrary.org/obo/go/shapes/Individual",
          "reason": "OR expression not satisfied:"
        },
        {
          "kind": "shex_nonconformant",
          "node": "",
          "shape": "http://purl.obolibrary.org/obo/go/shapes/Individual",
          "reason": "OR expression not satisfied:"
        }
      ],
      "since_commit": "9b9a1213bb939b37f04da70a79069fdb0ab46110",
      "since_date": "2026-05-04T11:33:35.886Z"
    },
    {
      "id": "go_cam_shape",
      "kind": "go_cam_shape",
      "label": "GO-CAM Shape",
      "severity": "error",
      "status": "fail",
      "ran_at": "2026-05-07T04:25:48.132Z",
      "violations": [
        {
          "kind": "shex_nonconformant",
          "node": "http://model.geneontology.org/MGI_MGI_1330290/6757e21a-76e8-49d4-bf7b-31a705dd49f5",
          "shape": "http://purl.obolibrary.org/obo/go/shapes/MolecularFunction",
          "reason": "OR expression not satisfied:"
        },
        {
          "kind": "shex_nonconformant",
          "node": "http://model.geneontology.org/MGI_MGI_1330290/68477655-9b1b-463a-805b-8225c4d0400e",
          "shape": "http://purl.obolibrary.org/obo/go/shapes/MolecularFunction",
          "reason": "OR expression not satisfied:"
        },
        {
          "kind": "shex_nonconformant",
          "node": "http://model.geneontology.org/MGI_MGI_1330290/615375ec-31cc-4726-9cf1-4c01d3aa1747",
          "shape": "http://purl.obolibrary.org/obo/go/shapes/MolecularFunction",
          "reason": "OR expression not satisfied:"
        },
        {
          "kind": "shex_nonconformant",
          "node": "http://model.geneontology.org/MGI_MGI_1330290/3ee0d4b5-8a2b-4189-ad22-3284943db703",
          "shape": "http://purl.obolibrary.org/obo/go/shapes/BiologicalProcess",
          "reason": "Cardinality violation (min=1): 0"
        },
        {
          "kind": "shex_nonconformant",
          "node": "http://model.geneontology.org/MGI_MGI_1330290/a815176d-7425-4072-ac61-3dc5e58f46ee",
          "shape": "http://purl.obolibrary.org/obo/go/shapes/BiologicalProcess",
          "reason": "Cardinality violation (min=1): 0"
        },
        {
          "kind": "shex_nonconformant",
          "node": "http://model.geneontology.org/MGI_MGI_1330290/0f53b86c-0633-47cb-b90a-1187f39e8d48",
          "shape": "http://purl.obolibrary.org/obo/go/shapes/BiologicalProcess",
          "reason": "Cardinality violation (min=1): 0"
        },
        {
          "kind": "shex_nonconformant",
          "node": "http://model.geneontology.org/MGI_MGI_1330290/9ead05e4-3548-40d6-9d4b-4a61a13d4316",
          "shape": "http://purl.obolibrary.org/obo/go/shapes/BiologicalProcess",
          "reason": "Cardinality violation (min=1): 0"
        },
        {
          "kind": "shex_nonconformant",
          "node": "http://model.geneontology.org/MGI_MGI_1330290/1971cb7c-19b3-4baf-98b8-05b87d37868f",
          "shape": "http://purl.obolibrary.org/obo/go/shapes/AnatomicalStructureDevelopment",
          "reason": "Cardinality violation (min=1): 0"
        },
        {
          "kind": "shex_nonconformant",
          "node": "http://model.geneontology.org/MGI_MGI_1330290/1141fd31-91c6-48e3-b70f-287ce97ee6b9",
          "shape": "http://purl.obolibrary.org/obo/go/shapes/AnatomicalStructureDevelopment",
          "reason": "Cardinality violation (min=1): 0"
        }
      ],
      "since_commit": "6a58093f893945d7b084fc8366587fd8596d7cb4",
      "since_date": "2026-05-07T15:05:09.385Z"
    },
    {
      "id": "disconnected_individuals",
      "kind": "sparql",
      "label": "Disconnected Individuals",
      "severity": "warning",
      "status": "pass",
      "ran_at": "2026-05-07T04:25:48.132Z",
      "violations": [],
      "last_passed_commit": "9b9a1213bb939b37f04da70a79069fdb0ab46110",
      "last_passed_date": "2026-05-04T11:33:35.886Z"
    },
    {
      "id": "multiply_reified_edges",
      "kind": "sparql",
      "label": "Multiply Reified Edges",
      "severity": "warning",
      "status": "pass",
      "ran_at": "2026-05-07T04:25:48.132Z",
      "violations": [],
      "last_passed_commit": "9b9a1213bb939b37f04da70a79069fdb0ab46110",
      "last_passed_date": "2026-05-04T11:33:35.886Z"
    }
  ]
}