{
  "id": "MGI_MGI_1347090",
  "iri": "http://model.geneontology.org/MGI_MGI_1347090",
  "ttl_path": "models/MGI_MGI_1347090.ttl",
  "master_sha": "6a58093f893945d7b084fc8366587fd8596d7cb4",
  "generated_at": "2026-05-07T15:05:09.385Z",
  "metadata": {
    "title": "Anxa10 (MGI:MGI:1347090)",
    "modelstate": "production",
    "deprecated": false,
    "date": "2007-10-15",
    "contributors": [
      {
        "orcid": "https://orcid.org/0000-0003-2689-5511"
      }
    ],
    "providers": [
      {
        "iri": "http://informatics.jax.org"
      }
    ],
    "taxon": null,
    "taxon_label": null
  },
  "checks": [
    {
      "id": "rdf_valid",
      "kind": "rdf_valid",
      "label": "RDF Validity",
      "severity": "warning",
      "status": "pass",
      "ran_at": "2026-05-07T04:25:48.132Z",
      "violations": [],
      "last_passed_commit": "6a58093f893945d7b084fc8366587fd8596d7cb4",
      "last_passed_date": "2026-05-07T15:05:09.385Z"
    },
    {
      "id": "owl_consistency",
      "kind": "owl_consistency",
      "label": "OWL Consistency",
      "severity": "error",
      "status": "pass",
      "ran_at": "2026-05-07T04:25:48.132Z",
      "violations": [],
      "last_passed_commit": "6a58093f893945d7b084fc8366587fd8596d7cb4",
      "last_passed_date": "2026-05-07T15:05:09.385Z"
    },
    {
      "id": "gpad_compatibility",
      "kind": "gpad_compatibility",
      "label": "GPAD Compatibility",
      "severity": "info",
      "pass_label": "GPAD-compatible",
      "fail_label": "Causal model",
      "unknown_label": "Unknown shape",
      "status": "pass",
      "ran_at": "2026-05-07T04:25:48.132Z",
      "violations": [],
      "last_passed_commit": "9b9a1213bb939b37f04da70a79069fdb0ab46110",
      "last_passed_date": "2026-05-04T11:33:35.886Z"
    },
    {
      "id": "go_cam_shape",
      "kind": "go_cam_shape",
      "label": "GO-CAM Shape",
      "severity": "error",
      "status": "fail",
      "ran_at": "2026-05-07T04:25:48.132Z",
      "violations": [
        {
          "kind": "shex_nonconformant",
          "node": "http://model.geneontology.org/MGI_MGI_1347090/b8b981e1-0645-482c-bbe4-4fb10a62f246",
          "shape": "http://purl.obolibrary.org/obo/go/shapes/InformationBiomacromolecule",
          "reason": "Cardinality violation (min=1): 0"
        },
        {
          "kind": "shex_nonconformant",
          "node": "http://model.geneontology.org/MGI_MGI_1347090/76fd5736-744c-4a26-8fbf-9ce7ba66221a",
          "shape": "http://purl.obolibrary.org/obo/go/shapes/InformationBiomacromolecule",
          "reason": "Cardinality violation (min=1): 0"
        },
        {
          "kind": "shex_nonconformant",
          "node": "http://model.geneontology.org/MGI_MGI_1347090/712ba24e-1e66-44c1-aeb1-98d695e20bba",
          "shape": "http://purl.obolibrary.org/obo/go/shapes/InformationBiomacromolecule",
          "reason": "Cardinality violation (min=1): 0"
        },
        {
          "kind": "shex_nonconformant",
          "node": "http://model.geneontology.org/MGI_MGI_1347090/4e7c3919-6dc4-469f-82d9-0057aa3cd212",
          "shape": "http://purl.obolibrary.org/obo/go/shapes/InformationBiomacromolecule",
          "reason": "Cardinality violation (min=1): 0"
        },
        {
          "kind": "shex_nonconformant",
          "node": "http://model.geneontology.org/MGI_MGI_1347090/dd28f808-d2ec-4b87-8cb0-b83b4b085693",
          "shape": "http://purl.obolibrary.org/obo/go/shapes/CellularComponent",
          "reason": "Cardinality violation (min=1): 0"
        },
        {
          "kind": "shex_nonconformant",
          "node": "http://model.geneontology.org/MGI_MGI_1347090/996332a0-c057-4257-9496-2cee03af3b2e",
          "shape": "http://purl.obolibrary.org/obo/go/shapes/CellularComponent",
          "reason": "Cardinality violation (min=1): 0"
        },
        {
          "kind": "shex_nonconformant",
          "node": "http://model.geneontology.org/MGI_MGI_1347090/6a4082b5-891b-43fa-984e-b3195fdcc009",
          "shape": "http://purl.obolibrary.org/obo/go/shapes/CellularComponent",
          "reason": "Cardinality violation (min=1): 0"
        },
        {
          "kind": "shex_nonconformant",
          "node": "http://model.geneontology.org/MGI_MGI_1347090/5f304d9c-d3c6-41e9-851c-29c5a38e8497",
          "shape": "http://purl.obolibrary.org/obo/go/shapes/CellularComponent",
          "reason": "Cardinality violation (min=1): 0"
        }
      ],
      "since_commit": "6a58093f893945d7b084fc8366587fd8596d7cb4",
      "since_date": "2026-05-07T15:05:09.385Z"
    },
    {
      "id": "disconnected_individuals",
      "kind": "sparql",
      "label": "Disconnected Individuals",
      "severity": "warning",
      "status": "pass",
      "ran_at": "2026-05-07T04:25:48.132Z",
      "violations": [],
      "last_passed_commit": "9b9a1213bb939b37f04da70a79069fdb0ab46110",
      "last_passed_date": "2026-05-04T11:33:35.886Z"
    },
    {
      "id": "multiply_reified_edges",
      "kind": "sparql",
      "label": "Multiply Reified Edges",
      "severity": "warning",
      "status": "pass",
      "ran_at": "2026-05-07T04:25:48.132Z",
      "violations": [],
      "last_passed_commit": "9b9a1213bb939b37f04da70a79069fdb0ab46110",
      "last_passed_date": "2026-05-04T11:33:35.886Z"
    }
  ]
}