{
  "id": "MGI_MGI_96203",
  "iri": "http://model.geneontology.org/MGI_MGI_96203",
  "ttl_path": "models/MGI_MGI_96203.ttl",
  "master_sha": "6a58093f893945d7b084fc8366587fd8596d7cb4",
  "generated_at": "2026-05-07T15:05:09.385Z",
  "metadata": {
    "title": "Hoxd11 (MGI:MGI:96203)",
    "modelstate": "production",
    "deprecated": false,
    "date": "2022-04-14",
    "comment": "Automated change 2022-04-14: <http://purl.obolibrary.org/obo/EMAPA_17207> replaced_by <http://purl.obolibrary.org/obo/EMAPA_17373>",
    "contributors": [
      {
        "orcid": "https://orcid.org/0000-0003-3394-9805"
      },
      {
        "orcid": "https://orcid.org/0000-0002-5741-7128"
      },
      {
        "orcid": "https://orcid.org/0000-0001-7476-6306"
      },
      {
        "orcid": "https://orcid.org/0000-0003-2689-5511"
      }
    ],
    "providers": [
      {
        "iri": "http://informatics.jax.org"
      }
    ],
    "taxon": null,
    "taxon_label": null
  },
  "checks": [
    {
      "id": "rdf_valid",
      "kind": "rdf_valid",
      "label": "RDF Validity",
      "severity": "warning",
      "status": "pass",
      "ran_at": "2026-05-07T04:25:48.132Z",
      "violations": [],
      "last_passed_commit": "6a58093f893945d7b084fc8366587fd8596d7cb4",
      "last_passed_date": "2026-05-07T15:05:09.385Z"
    },
    {
      "id": "owl_consistency",
      "kind": "owl_consistency",
      "label": "OWL Consistency",
      "severity": "error",
      "status": "pass",
      "ran_at": "2026-05-07T04:25:48.132Z",
      "violations": [],
      "last_passed_commit": "6a58093f893945d7b084fc8366587fd8596d7cb4",
      "last_passed_date": "2026-05-07T15:05:09.385Z"
    },
    {
      "id": "gpad_compatibility",
      "kind": "gpad_compatibility",
      "label": "GPAD Compatibility",
      "severity": "info",
      "pass_label": "GPAD-compatible",
      "fail_label": "Causal model",
      "unknown_label": "Unknown shape",
      "status": "fail",
      "ran_at": "2026-05-07T04:25:48.132Z",
      "violations": [
        {
          "kind": "shex_nonconformant",
          "node": "",
          "shape": "http://purl.obolibrary.org/obo/go/shapes/Individual",
          "reason": "OR expression not satisfied:"
        },
        {
          "kind": "shex_nonconformant",
          "node": "",
          "shape": "http://purl.obolibrary.org/obo/go/shapes/Individual",
          "reason": "OR expression not satisfied:"
        },
        {
          "kind": "shex_nonconformant",
          "node": "",
          "shape": "http://purl.obolibrary.org/obo/go/shapes/Individual",
          "reason": "OR expression not satisfied:"
        },
        {
          "kind": "shex_nonconformant",
          "node": "",
          "shape": "http://purl.obolibrary.org/obo/go/shapes/Individual",
          "reason": "OR expression not satisfied:"
        },
        {
          "kind": "shex_nonconformant",
          "node": "",
          "shape": "http://purl.obolibrary.org/obo/go/shapes/Individual",
          "reason": "OR expression not satisfied:"
        },
        {
          "kind": "shex_nonconformant",
          "node": "",
          "shape": "http://purl.obolibrary.org/obo/go/shapes/Individual",
          "reason": "OR expression not satisfied:"
        },
        {
          "kind": "shex_nonconformant",
          "node": "",
          "shape": "http://purl.obolibrary.org/obo/go/shapes/Individual",
          "reason": "OR expression not satisfied:"
        },
        {
          "kind": "shex_nonconformant",
          "node": "",
          "shape": "http://purl.obolibrary.org/obo/go/shapes/Individual",
          "reason": "OR expression not satisfied:"
        },
        {
          "kind": "shex_nonconformant",
          "node": "",
          "shape": "http://purl.obolibrary.org/obo/go/shapes/Individual",
          "reason": "OR expression not satisfied:"
        },
        {
          "kind": "shex_nonconformant",
          "node": "",
          "shape": "http://purl.obolibrary.org/obo/go/shapes/Individual",
          "reason": "OR expression not satisfied:"
        },
        {
          "kind": "shex_nonconformant",
          "node": "",
          "shape": "http://purl.obolibrary.org/obo/go/shapes/Individual",
          "reason": "OR expression not satisfied:"
        },
        {
          "kind": "shex_nonconformant",
          "node": "",
          "shape": "http://purl.obolibrary.org/obo/go/shapes/Individual",
          "reason": "OR expression not satisfied:"
        },
        {
          "kind": "shex_nonconformant",
          "node": "",
          "shape": "http://purl.obolibrary.org/obo/go/shapes/Individual",
          "reason": "OR expression not satisfied:"
        },
        {
          "kind": "shex_nonconformant",
          "node": "",
          "shape": "http://purl.obolibrary.org/obo/go/shapes/Individual",
          "reason": "OR expression not satisfied:"
        },
        {
          "kind": "shex_nonconformant",
          "node": "",
          "shape": "http://purl.obolibrary.org/obo/go/shapes/Individual",
          "reason": "OR expression not satisfied:"
        },
        {
          "kind": "shex_nonconformant",
          "node": "",
          "shape": "http://purl.obolibrary.org/obo/go/shapes/Individual",
          "reason": "OR expression not satisfied:"
        },
        {
          "kind": "shex_nonconformant",
          "node": "",
          "shape": "http://purl.obolibrary.org/obo/go/shapes/Individual",
          "reason": "OR expression not satisfied:"
        },
        {
          "kind": "shex_nonconformant",
          "node": "",
          "shape": "http://purl.obolibrary.org/obo/go/shapes/Individual",
          "reason": "OR expression not satisfied:"
        },
        {
          "kind": "shex_nonconformant",
          "node": "",
          "shape": "http://purl.obolibrary.org/obo/go/shapes/Individual",
          "reason": "OR expression not satisfied:"
        },
        {
          "kind": "shex_nonconformant",
          "node": "",
          "shape": "http://purl.obolibrary.org/obo/go/shapes/Individual",
          "reason": "OR expression not satisfied:"
        },
        {
          "kind": "shex_nonconformant",
          "node": "",
          "shape": "http://purl.obolibrary.org/obo/go/shapes/Individual",
          "reason": "OR expression not satisfied:"
        },
        {
          "kind": "shex_nonconformant",
          "node": "",
          "shape": "http://purl.obolibrary.org/obo/go/shapes/Individual",
          "reason": "OR expression not satisfied:"
        },
        {
          "kind": "shex_nonconformant",
          "node": "",
          "shape": "http://purl.obolibrary.org/obo/go/shapes/Individual",
          "reason": "OR expression not satisfied:"
        },
        {
          "kind": "shex_nonconformant",
          "node": "",
          "shape": "http://purl.obolibrary.org/obo/go/shapes/Individual",
          "reason": "OR expression not satisfied:"
        },
        {
          "kind": "shex_nonconformant",
          "node": "",
          "shape": "http://purl.obolibrary.org/obo/go/shapes/Individual",
          "reason": "OR expression not satisfied:"
        },
        {
          "kind": "shex_nonconformant",
          "node": "",
          "shape": "http://purl.obolibrary.org/obo/go/shapes/Individual",
          "reason": "OR expression not satisfied:"
        },
        {
          "kind": "shex_nonconformant",
          "node": "",
          "shape": "http://purl.obolibrary.org/obo/go/shapes/Individual",
          "reason": "OR expression not satisfied:"
        },
        {
          "kind": "shex_nonconformant",
          "node": "",
          "shape": "http://purl.obolibrary.org/obo/go/shapes/Individual",
          "reason": "OR expression not satisfied:"
        },
        {
          "kind": "shex_nonconformant",
          "node": "",
          "shape": "http://purl.obolibrary.org/obo/go/shapes/Individual",
          "reason": "OR expression not satisfied:"
        },
        {
          "kind": "shex_nonconformant",
          "node": "",
          "shape": "http://purl.obolibrary.org/obo/go/shapes/Individual",
          "reason": "OR expression not satisfied:"
        },
        {
          "kind": "shex_nonconformant",
          "node": "",
          "shape": "http://purl.obolibrary.org/obo/go/shapes/Individual",
          "reason": "OR expression not satisfied:"
        },
        {
          "kind": "shex_nonconformant",
          "node": "",
          "shape": "http://purl.obolibrary.org/obo/go/shapes/Individual",
          "reason": "OR expression not satisfied:"
        },
        {
          "kind": "shex_nonconformant",
          "node": "",
          "shape": "http://purl.obolibrary.org/obo/go/shapes/Individual",
          "reason": "OR expression not satisfied:"
        },
        {
          "kind": "shex_nonconformant",
          "node": "",
          "shape": "http://purl.obolibrary.org/obo/go/shapes/Individual",
          "reason": "OR expression not satisfied:"
        },
        {
          "kind": "shex_nonconformant",
          "node": "",
          "shape": "http://purl.obolibrary.org/obo/go/shapes/Individual",
          "reason": "OR expression not satisfied:"
        },
        {
          "kind": "shex_nonconformant",
          "node": "",
          "shape": "http://purl.obolibrary.org/obo/go/shapes/Individual",
          "reason": "OR expression not satisfied:"
        },
        {
          "kind": "shex_nonconformant",
          "node": "",
          "shape": "http://purl.obolibrary.org/obo/go/shapes/Individual",
          "reason": "OR expression not satisfied:"
        },
        {
          "kind": "shex_nonconformant",
          "node": "",
          "shape": "http://purl.obolibrary.org/obo/go/shapes/Individual",
          "reason": "OR expression not satisfied:"
        },
        {
          "kind": "shex_nonconformant",
          "node": "",
          "shape": "http://purl.obolibrary.org/obo/go/shapes/Individual",
          "reason": "OR expression not satisfied:"
        },
        {
          "kind": "shex_nonconformant",
          "node": "",
          "shape": "http://purl.obolibrary.org/obo/go/shapes/Individual",
          "reason": "OR expression not satisfied:"
        },
        {
          "kind": "shex_nonconformant",
          "node": "",
          "shape": "http://purl.obolibrary.org/obo/go/shapes/Individual",
          "reason": "OR expression not satisfied:"
        },
        {
          "kind": "shex_nonconformant",
          "node": "",
          "shape": "http://purl.obolibrary.org/obo/go/shapes/Individual",
          "reason": "OR expression not satisfied:"
        },
        {
          "kind": "shex_nonconformant",
          "node": "",
          "shape": "http://purl.obolibrary.org/obo/go/shapes/Individual",
          "reason": "OR expression not satisfied:"
        },
        {
          "kind": "shex_nonconformant",
          "node": "",
          "shape": "http://purl.obolibrary.org/obo/go/shapes/Individual",
          "reason": "OR expression not satisfied:"
        },
        {
          "kind": "shex_nonconformant",
          "node": "",
          "shape": "http://purl.obolibrary.org/obo/go/shapes/Individual",
          "reason": "OR expression not satisfied:"
        },
        {
          "kind": "shex_nonconformant",
          "node": "",
          "shape": "http://purl.obolibrary.org/obo/go/shapes/Individual",
          "reason": "OR expression not satisfied:"
        },
        {
          "kind": "shex_nonconformant",
          "node": "",
          "shape": "http://purl.obolibrary.org/obo/go/shapes/Individual",
          "reason": "OR expression not satisfied:"
        },
        {
          "kind": "shex_nonconformant",
          "node": "",
          "shape": "http://purl.obolibrary.org/obo/go/shapes/Individual",
          "reason": "OR expression not satisfied:"
        },
        {
          "kind": "shex_nonconformant",
          "node": "",
          "shape": "http://purl.obolibrary.org/obo/go/shapes/Individual",
          "reason": "OR expression not satisfied:"
        },
        {
          "kind": "shex_nonconformant",
          "node": "",
          "shape": "http://purl.obolibrary.org/obo/go/shapes/Individual",
          "reason": "OR expression not satisfied:"
        },
        {
          "kind": "shex_nonconformant",
          "node": "",
          "shape": "http://purl.obolibrary.org/obo/go/shapes/Individual",
          "reason": "OR expression not satisfied:"
        },
        {
          "kind": "shex_nonconformant",
          "node": "",
          "shape": "http://purl.obolibrary.org/obo/go/shapes/Individual",
          "reason": "OR expression not satisfied:"
        },
        {
          "kind": "shex_nonconformant",
          "node": "",
          "shape": "http://purl.obolibrary.org/obo/go/shapes/Individual",
          "reason": "OR expression not satisfied:"
        },
        {
          "kind": "shex_nonconformant",
          "node": "",
          "shape": "http://purl.obolibrary.org/obo/go/shapes/Individual",
          "reason": "OR expression not satisfied:"
        },
        {
          "kind": "shex_nonconformant",
          "node": "",
          "shape": "http://purl.obolibrary.org/obo/go/shapes/Individual",
          "reason": "OR expression not satisfied:"
        },
        {
          "kind": "shex_nonconformant",
          "node": "",
          "shape": "http://purl.obolibrary.org/obo/go/shapes/Individual",
          "reason": "OR expression not satisfied:"
        },
        {
          "kind": "shex_nonconformant",
          "node": "",
          "shape": "http://purl.obolibrary.org/obo/go/shapes/Individual",
          "reason": "OR expression not satisfied:"
        },
        {
          "kind": "shex_nonconformant",
          "node": "",
          "shape": "http://purl.obolibrary.org/obo/go/shapes/Individual",
          "reason": "OR expression not satisfied:"
        },
        {
          "kind": "shex_nonconformant",
          "node": "",
          "shape": "http://purl.obolibrary.org/obo/go/shapes/Individual",
          "reason": "OR expression not satisfied:"
        },
        {
          "kind": "shex_nonconformant",
          "node": "",
          "shape": "http://purl.obolibrary.org/obo/go/shapes/Individual",
          "reason": "OR expression not satisfied:"
        },
        {
          "kind": "shex_nonconformant",
          "node": "",
          "shape": "http://purl.obolibrary.org/obo/go/shapes/Individual",
          "reason": "OR expression not satisfied:"
        },
        {
          "kind": "shex_nonconformant",
          "node": "",
          "shape": "http://purl.obolibrary.org/obo/go/shapes/Individual",
          "reason": "OR expression not satisfied:"
        },
        {
          "kind": "shex_nonconformant",
          "node": "",
          "shape": "http://purl.obolibrary.org/obo/go/shapes/Individual",
          "reason": "OR expression not satisfied:"
        },
        {
          "kind": "shex_nonconformant",
          "node": "",
          "shape": "http://purl.obolibrary.org/obo/go/shapes/Individual",
          "reason": "OR expression not satisfied:"
        },
        {
          "kind": "shex_nonconformant",
          "node": "",
          "shape": "http://purl.obolibrary.org/obo/go/shapes/Individual",
          "reason": "OR expression not satisfied:"
        },
        {
          "kind": "shex_nonconformant",
          "node": "",
          "shape": "http://purl.obolibrary.org/obo/go/shapes/Individual",
          "reason": "OR expression not satisfied:"
        },
        {
          "kind": "shex_nonconformant",
          "node": "",
          "shape": "http://purl.obolibrary.org/obo/go/shapes/Individual",
          "reason": "OR expression not satisfied:"
        },
        {
          "kind": "shex_nonconformant",
          "node": "",
          "shape": "http://purl.obolibrary.org/obo/go/shapes/Individual",
          "reason": "OR expression not satisfied:"
        },
        {
          "kind": "shex_nonconformant",
          "node": "",
          "shape": "http://purl.obolibrary.org/obo/go/shapes/Individual",
          "reason": "OR expression not satisfied:"
        },
        {
          "kind": "shex_nonconformant",
          "node": "",
          "shape": "http://purl.obolibrary.org/obo/go/shapes/Individual",
          "reason": "OR expression not satisfied:"
        },
        {
          "kind": "shex_nonconformant",
          "node": "",
          "shape": "http://purl.obolibrary.org/obo/go/shapes/Individual",
          "reason": "OR expression not satisfied:"
        },
        {
          "kind": "shex_nonconformant",
          "node": "",
          "shape": "http://purl.obolibrary.org/obo/go/shapes/Individual",
          "reason": "OR expression not satisfied:"
        },
        {
          "kind": "shex_nonconformant",
          "node": "",
          "shape": "http://purl.obolibrary.org/obo/go/shapes/Individual",
          "reason": "OR expression not satisfied:"
        },
        {
          "kind": "shex_nonconformant",
          "node": "",
          "shape": "http://purl.obolibrary.org/obo/go/shapes/Individual",
          "reason": "OR expression not satisfied:"
        },
        {
          "kind": "shex_nonconformant",
          "node": "",
          "shape": "http://purl.obolibrary.org/obo/go/shapes/Individual",
          "reason": "OR expression not satisfied:"
        },
        {
          "kind": "shex_nonconformant",
          "node": "",
          "shape": "http://purl.obolibrary.org/obo/go/shapes/Individual",
          "reason": "OR expression not satisfied:"
        },
        {
          "kind": "shex_nonconformant",
          "node": "",
          "shape": "http://purl.obolibrary.org/obo/go/shapes/Individual",
          "reason": "OR expression not satisfied:"
        },
        {
          "kind": "shex_nonconformant",
          "node": "",
          "shape": "http://purl.obolibrary.org/obo/go/shapes/Individual",
          "reason": "OR expression not satisfied:"
        }
      ],
      "since_commit": "9b9a1213bb939b37f04da70a79069fdb0ab46110",
      "since_date": "2026-05-04T11:33:35.886Z"
    },
    {
      "id": "go_cam_shape",
      "kind": "go_cam_shape",
      "label": "GO-CAM Shape",
      "severity": "error",
      "status": "fail",
      "ran_at": "2026-05-07T04:25:48.132Z",
      "violations": [
        {
          "kind": "shex_nonconformant",
          "node": "http://model.geneontology.org/MGI_MGI_96203/0abd6984-48bc-4a03-9fa1-25d534111e69",
          "shape": "http://purl.obolibrary.org/obo/go/shapes/MolecularFunction",
          "reason": "OR expression not satisfied:"
        },
        {
          "kind": "shex_nonconformant",
          "node": "http://model.geneontology.org/MGI_MGI_96203/d7d5be45-9ad4-4755-b5b2-642c71e5f293",
          "shape": "http://purl.obolibrary.org/obo/go/shapes/MolecularFunction",
          "reason": "OR expression not satisfied:"
        },
        {
          "kind": "shex_nonconformant",
          "node": "http://model.geneontology.org/MGI_MGI_96203/52825d6d-0bff-4197-808d-40d878aaa412",
          "shape": "http://purl.obolibrary.org/obo/go/shapes/MolecularFunction",
          "reason": "OR expression not satisfied:"
        },
        {
          "kind": "shex_nonconformant",
          "node": "http://model.geneontology.org/MGI_MGI_96203/df3ec9e2-07c9-4c3c-a3ed-6dd7752d5a09",
          "shape": "http://purl.obolibrary.org/obo/go/shapes/MolecularFunction",
          "reason": "OR expression not satisfied:"
        },
        {
          "kind": "shex_nonconformant",
          "node": "http://model.geneontology.org/MGI_MGI_96203/2d1316aa-49a6-4a63-a6cc-6722ede97250",
          "shape": "http://purl.obolibrary.org/obo/go/shapes/MolecularFunction",
          "reason": "OR expression not satisfied:"
        },
        {
          "kind": "shex_nonconformant",
          "node": "http://model.geneontology.org/MGI_MGI_96203/315bbd56-d296-4e61-8a68-dc65ca3f7508",
          "shape": "http://purl.obolibrary.org/obo/go/shapes/MolecularFunction",
          "reason": "OR expression not satisfied:"
        },
        {
          "kind": "shex_nonconformant",
          "node": "http://model.geneontology.org/MGI_MGI_96203/8799f376-03bc-4145-9846-68a8897536f6",
          "shape": "http://purl.obolibrary.org/obo/go/shapes/MolecularFunction",
          "reason": "OR expression not satisfied:"
        },
        {
          "kind": "shex_nonconformant",
          "node": "http://model.geneontology.org/MGI_MGI_96203/344110ef-d9e1-4ed1-b38d-37596dfea7e8",
          "shape": "http://purl.obolibrary.org/obo/go/shapes/MolecularFunction",
          "reason": "OR expression not satisfied:"
        },
        {
          "kind": "shex_nonconformant",
          "node": "http://model.geneontology.org/MGI_MGI_96203/83488f06-e237-4cc7-9436-5b3668289de2",
          "shape": "http://purl.obolibrary.org/obo/go/shapes/MolecularFunction",
          "reason": "OR expression not satisfied:"
        },
        {
          "kind": "shex_nonconformant",
          "node": "http://model.geneontology.org/MGI_MGI_96203/1b05c2ab-bcdc-4904-bdbd-a04e406b0522",
          "shape": "http://purl.obolibrary.org/obo/go/shapes/MolecularFunction",
          "reason": "OR expression not satisfied:"
        },
        {
          "kind": "shex_nonconformant",
          "node": "http://model.geneontology.org/MGI_MGI_96203/6e3c5acd-80a3-4980-b843-3b8c93ba2b59",
          "shape": "http://purl.obolibrary.org/obo/go/shapes/MolecularFunction",
          "reason": "OR expression not satisfied:"
        },
        {
          "kind": "shex_nonconformant",
          "node": "http://model.geneontology.org/MGI_MGI_96203/371ca746-a6ee-4bff-b654-ed9b4cb1540f",
          "shape": "http://purl.obolibrary.org/obo/go/shapes/MolecularFunction",
          "reason": "OR expression not satisfied:"
        },
        {
          "kind": "shex_nonconformant",
          "node": "http://model.geneontology.org/MGI_MGI_96203/e7faef65-021d-46ed-b3e2-2f65a05ec879",
          "shape": "http://purl.obolibrary.org/obo/go/shapes/MolecularFunction",
          "reason": "OR expression not satisfied:"
        },
        {
          "kind": "shex_nonconformant",
          "node": "http://model.geneontology.org/MGI_MGI_96203/d0519d78-c070-4c3b-843c-1766206fbbca",
          "shape": "http://purl.obolibrary.org/obo/go/shapes/BiologicalProcess",
          "reason": "Cardinality violation (min=1): 0"
        },
        {
          "kind": "shex_nonconformant",
          "node": "http://model.geneontology.org/MGI_MGI_96203/ead51916-ae0a-4177-b1cc-aa322b755e49",
          "shape": "http://purl.obolibrary.org/obo/go/shapes/BiologicalProcess",
          "reason": "Cardinality violation (min=1): 0"
        },
        {
          "kind": "shex_nonconformant",
          "node": "http://model.geneontology.org/MGI_MGI_96203/e07e9b76-39da-4204-8c23-de51312cee01",
          "shape": "http://purl.obolibrary.org/obo/go/shapes/BiologicalProcess",
          "reason": "Cardinality violation (min=1): 0"
        },
        {
          "kind": "shex_nonconformant",
          "node": "http://model.geneontology.org/MGI_MGI_96203/9d04dfbe-9ce9-45d1-8602-1c02833c0fdc",
          "shape": "http://purl.obolibrary.org/obo/go/shapes/BiologicalProcess",
          "reason": "Cardinality violation (min=1): 0"
        },
        {
          "kind": "shex_nonconformant",
          "node": "http://model.geneontology.org/MGI_MGI_96203/8a240a91-d666-4315-8df8-a8db07d846aa",
          "shape": "http://purl.obolibrary.org/obo/go/shapes/BiologicalProcess",
          "reason": "Cardinality violation (min=1): 0"
        },
        {
          "kind": "shex_nonconformant",
          "node": "http://model.geneontology.org/MGI_MGI_96203/634c91d6-5b4f-4630-9875-6467cfae9205",
          "shape": "http://purl.obolibrary.org/obo/go/shapes/BiologicalProcess",
          "reason": "Cardinality violation (min=1): 0"
        },
        {
          "kind": "shex_nonconformant",
          "node": "http://model.geneontology.org/MGI_MGI_96203/2bd92772-0729-4d93-8419-f6badc3e97d9",
          "shape": "http://purl.obolibrary.org/obo/go/shapes/BiologicalProcess",
          "reason": "Cardinality violation (min=1): 0"
        },
        {
          "kind": "shex_nonconformant",
          "node": "http://model.geneontology.org/MGI_MGI_96203/af0fc659-e150-4b08-b0a4-12279ed26c33",
          "shape": "http://purl.obolibrary.org/obo/go/shapes/BiologicalProcess",
          "reason": "Cardinality violation (min=1): 0"
        },
        {
          "kind": "shex_nonconformant",
          "node": "http://model.geneontology.org/MGI_MGI_96203/a82f6e91-baaf-4ea0-91bf-731250a3eb2e",
          "shape": "http://purl.obolibrary.org/obo/go/shapes/BiologicalProcess",
          "reason": "Cardinality violation (min=1): 0"
        },
        {
          "kind": "shex_nonconformant",
          "node": "http://model.geneontology.org/MGI_MGI_96203/f4f9fdc0-ef60-44ea-9c8d-851be997c29c",
          "shape": "http://purl.obolibrary.org/obo/go/shapes/BiologicalProcess",
          "reason": "Cardinality violation (min=1): 0"
        },
        {
          "kind": "shex_nonconformant",
          "node": "http://model.geneontology.org/MGI_MGI_96203/8c2c242f-f0e7-48e0-bc8c-ebffd5f8c16c",
          "shape": "http://purl.obolibrary.org/obo/go/shapes/BiologicalProcess",
          "reason": "Cardinality violation (min=1): 0"
        },
        {
          "kind": "shex_nonconformant",
          "node": "http://model.geneontology.org/MGI_MGI_96203/9e3ba371-55c6-4e4f-b965-2b34f46bf589",
          "shape": "http://purl.obolibrary.org/obo/go/shapes/BiologicalProcess",
          "reason": "OR expression not satisfied:"
        },
        {
          "kind": "shex_nonconformant",
          "node": "http://model.geneontology.org/MGI_MGI_96203/1df4fd2f-a8f1-4c0c-8272-a9a553daddd5",
          "shape": "http://purl.obolibrary.org/obo/go/shapes/BiologicalProcess",
          "reason": "Cardinality violation (min=1): 0"
        },
        {
          "kind": "shex_nonconformant",
          "node": "http://model.geneontology.org/MGI_MGI_96203/d6effdcd-d444-4ee0-86e7-c7b0a6739cef",
          "shape": "http://purl.obolibrary.org/obo/go/shapes/BiologicalProcess",
          "reason": "Cardinality violation (min=1): 0"
        },
        {
          "kind": "shex_nonconformant",
          "node": "http://model.geneontology.org/MGI_MGI_96203/67f540ee-ee97-4ae1-8d2d-f727050b9d05",
          "shape": "http://purl.obolibrary.org/obo/go/shapes/BiologicalProcess",
          "reason": "Cardinality violation (min=1): 0"
        },
        {
          "kind": "shex_nonconformant",
          "node": "http://model.geneontology.org/MGI_MGI_96203/3c0717ab-7e55-4952-93e1-f378f9a76dde",
          "shape": "http://purl.obolibrary.org/obo/go/shapes/AnatomicalStructureDevelopment",
          "reason": "Cardinality violation (min=1): 0"
        },
        {
          "kind": "shex_nonconformant",
          "node": "http://model.geneontology.org/MGI_MGI_96203/d62e31a4-ab5b-4e25-be13-e9adee617fce",
          "shape": "http://purl.obolibrary.org/obo/go/shapes/AnatomicalStructureDevelopment",
          "reason": "Cardinality violation (min=1): 0"
        },
        {
          "kind": "shex_nonconformant",
          "node": "http://model.geneontology.org/MGI_MGI_96203/649a23c9-4ad1-4ca5-a7fa-dfc7e34f4937",
          "shape": "http://purl.obolibrary.org/obo/go/shapes/AnatomicalStructureDevelopment",
          "reason": "Cardinality violation (min=1): 0"
        },
        {
          "kind": "shex_nonconformant",
          "node": "http://model.geneontology.org/MGI_MGI_96203/4f369ad3-2b88-4cb4-b711-3eff431fb6ff",
          "shape": "http://purl.obolibrary.org/obo/go/shapes/AnatomicalStructureDevelopment",
          "reason": "Cardinality violation (min=1): 0"
        },
        {
          "kind": "shex_nonconformant",
          "node": "http://model.geneontology.org/MGI_MGI_96203/7fe8cb24-406a-4bf7-ad0b-349ee780898e",
          "shape": "http://purl.obolibrary.org/obo/go/shapes/AnatomicalStructureDevelopment",
          "reason": "Cardinality violation (min=1): 0"
        },
        {
          "kind": "shex_nonconformant",
          "node": "http://model.geneontology.org/MGI_MGI_96203/120fe463-bdc1-4a97-9569-a0a789c1ab77",
          "shape": "http://purl.obolibrary.org/obo/go/shapes/AnatomicalStructureDevelopment",
          "reason": "Cardinality violation (min=1): 0"
        },
        {
          "kind": "shex_nonconformant",
          "node": "http://model.geneontology.org/MGI_MGI_96203/d81f5428-0fc6-470b-ae00-aeda3b90da40",
          "shape": "http://purl.obolibrary.org/obo/go/shapes/AnatomicalStructureDevelopment",
          "reason": "Cardinality violation (min=1): 0"
        },
        {
          "kind": "shex_nonconformant",
          "node": "http://model.geneontology.org/MGI_MGI_96203/a3672eb9-9193-47a0-b2c5-28e94eadb952",
          "shape": "http://purl.obolibrary.org/obo/go/shapes/AnatomicalStructureDevelopment",
          "reason": "Cardinality violation (min=1): 0"
        },
        {
          "kind": "shex_nonconformant",
          "node": "http://model.geneontology.org/MGI_MGI_96203/af0fc659-e150-4b08-b0a4-12279ed26c33",
          "shape": "http://purl.obolibrary.org/obo/go/shapes/AnatomicalStructureDevelopment",
          "reason": "Cardinality violation (min=1): 0"
        },
        {
          "kind": "shex_nonconformant",
          "node": "http://model.geneontology.org/MGI_MGI_96203/a82f6e91-baaf-4ea0-91bf-731250a3eb2e",
          "shape": "http://purl.obolibrary.org/obo/go/shapes/AnatomicalStructureDevelopment",
          "reason": "Cardinality violation (min=1): 0"
        },
        {
          "kind": "shex_nonconformant",
          "node": "http://model.geneontology.org/MGI_MGI_96203/f4f9fdc0-ef60-44ea-9c8d-851be997c29c",
          "shape": "http://purl.obolibrary.org/obo/go/shapes/Growth",
          "reason": "Cardinality violation (min=1): 0"
        },
        {
          "kind": "shex_nonconformant",
          "node": "http://model.geneontology.org/MGI_MGI_96203/8c2c242f-f0e7-48e0-bc8c-ebffd5f8c16c",
          "shape": "http://purl.obolibrary.org/obo/go/shapes/Growth",
          "reason": "Cardinality violation (min=1): 0"
        },
        {
          "kind": "shex_nonconformant",
          "node": "http://model.geneontology.org/MGI_MGI_96203/634c91d6-5b4f-4630-9875-6467cfae9205",
          "shape": "http://purl.obolibrary.org/obo/go/shapes/PatternSpecificationProcess",
          "reason": "Cardinality violation (min=1): 0"
        },
        {
          "kind": "shex_nonconformant",
          "node": "http://model.geneontology.org/MGI_MGI_96203/2bd92772-0729-4d93-8419-f6badc3e97d9",
          "shape": "http://purl.obolibrary.org/obo/go/shapes/PatternSpecificationProcess",
          "reason": "Cardinality violation (min=1): 0"
        },
        {
          "kind": "shex_nonconformant",
          "node": "http://model.geneontology.org/MGI_MGI_96203/d0519d78-c070-4c3b-843c-1766206fbbca",
          "shape": "http://purl.obolibrary.org/obo/go/shapes/PatternSpecificationProcess",
          "reason": "Cardinality violation (min=1): 0"
        },
        {
          "kind": "shex_nonconformant",
          "node": "http://model.geneontology.org/MGI_MGI_96203/ead51916-ae0a-4177-b1cc-aa322b755e49",
          "shape": "http://purl.obolibrary.org/obo/go/shapes/PatternSpecificationProcess",
          "reason": "Cardinality violation (min=1): 0"
        },
        {
          "kind": "shex_nonconformant",
          "node": "http://model.geneontology.org/MGI_MGI_96203/e07e9b76-39da-4204-8c23-de51312cee01",
          "shape": "http://purl.obolibrary.org/obo/go/shapes/PatternSpecificationProcess",
          "reason": "Cardinality violation (min=1): 0"
        },
        {
          "kind": "shex_nonconformant",
          "node": "http://model.geneontology.org/MGI_MGI_96203/9d04dfbe-9ce9-45d1-8602-1c02833c0fdc",
          "shape": "http://purl.obolibrary.org/obo/go/shapes/PatternSpecificationProcess",
          "reason": "Cardinality violation (min=1): 0"
        },
        {
          "kind": "shex_nonconformant",
          "node": "http://model.geneontology.org/MGI_MGI_96203/8a240a91-d666-4315-8df8-a8db07d846aa",
          "shape": "http://purl.obolibrary.org/obo/go/shapes/PatternSpecificationProcess",
          "reason": "Cardinality violation (min=1): 0"
        }
      ],
      "since_commit": "6a58093f893945d7b084fc8366587fd8596d7cb4",
      "since_date": "2026-05-07T15:05:09.385Z"
    },
    {
      "id": "disconnected_individuals",
      "kind": "sparql",
      "label": "Disconnected Individuals",
      "severity": "warning",
      "status": "pass",
      "ran_at": "2026-05-07T04:25:48.132Z",
      "violations": [],
      "last_passed_commit": "9b9a1213bb939b37f04da70a79069fdb0ab46110",
      "last_passed_date": "2026-05-04T11:33:35.886Z"
    },
    {
      "id": "multiply_reified_edges",
      "kind": "sparql",
      "label": "Multiply Reified Edges",
      "severity": "warning",
      "status": "pass",
      "ran_at": "2026-05-07T04:25:48.132Z",
      "violations": [],
      "last_passed_commit": "9b9a1213bb939b37f04da70a79069fdb0ab46110",
      "last_passed_date": "2026-05-04T11:33:35.886Z"
    }
  ]
}