{
  "id": "SYNGO_2114",
  "iri": "http://model.geneontology.org/SYNGO_2114",
  "ttl_path": "models/SYNGO_2114.ttl",
  "master_sha": "6a58093f893945d7b084fc8366587fd8596d7cb4",
  "generated_at": "2026-05-07T15:05:09.385Z",
  "metadata": {
    "title": "SYNGO_BP_2114",
    "modelstate": "production",
    "deprecated": false,
    "date": "2023-02-26",
    "comment": "Rationale: Fig.2: \"Endocannabinoid-Mediated Retrograde Suppression Is Absent in the Cerebellum of α-KO Mice\"\n\nFig.3: \"Endocannabinoid-Mediated Retrograde Suppression Is Absent in the Hippocampus and Striatum of α-KO Mice\"\n\nNote1: the retrograde aspect of the effect is demonstrated by the effect of depolarization of the postsynaptic cell that has effects on the presynaptic release of neurotransmitter.\nNote2: The effect is shown to be on GABAergic and Glutamatergic synaptic currents in the hippocampus and striatum. I did not have sufficient space in the menus to accomodate this combinatorial complexity.. Experimental description: \"Mice were decapitated following CO2 anesthesia, a...\"",
    "contributors": [
      {
        "orcid": "https://orcid.org/0000-0002-2514-0216"
      },
      {
        "orcid": "https://orcid.org/0000-0002-2286-1587"
      },
      {
        "orcid": "https://orcid.org/0000-0002-4973-5732"
      }
    ],
    "providers": [
      {
        "iri": "https://syngo.vu.nl"
      }
    ],
    "taxon": null,
    "taxon_label": null
  },
  "checks": [
    {
      "id": "rdf_valid",
      "kind": "rdf_valid",
      "label": "RDF Validity",
      "severity": "warning",
      "status": "pass",
      "ran_at": "2026-05-07T04:25:48.132Z",
      "violations": [],
      "last_passed_commit": "6a58093f893945d7b084fc8366587fd8596d7cb4",
      "last_passed_date": "2026-05-07T15:05:09.385Z"
    },
    {
      "id": "owl_consistency",
      "kind": "owl_consistency",
      "label": "OWL Consistency",
      "severity": "error",
      "status": "pass",
      "ran_at": "2026-05-07T04:25:48.132Z",
      "violations": [],
      "last_passed_commit": "6a58093f893945d7b084fc8366587fd8596d7cb4",
      "last_passed_date": "2026-05-07T15:05:09.385Z"
    },
    {
      "id": "gpad_compatibility",
      "kind": "gpad_compatibility",
      "label": "GPAD Compatibility",
      "severity": "info",
      "pass_label": "GPAD-compatible",
      "fail_label": "Causal model",
      "unknown_label": "Unknown shape",
      "status": "pass",
      "ran_at": "2026-05-07T04:25:48.132Z",
      "violations": [],
      "last_passed_commit": "9b9a1213bb939b37f04da70a79069fdb0ab46110",
      "last_passed_date": "2026-05-04T11:33:35.886Z"
    },
    {
      "id": "go_cam_shape",
      "kind": "go_cam_shape",
      "label": "GO-CAM Shape",
      "severity": "error",
      "status": "pass",
      "ran_at": "2026-05-07T04:25:48.132Z",
      "violations": [],
      "last_passed_commit": "6a58093f893945d7b084fc8366587fd8596d7cb4",
      "last_passed_date": "2026-05-07T15:05:09.385Z"
    },
    {
      "id": "disconnected_individuals",
      "kind": "sparql",
      "label": "Disconnected Individuals",
      "severity": "warning",
      "status": "pass",
      "ran_at": "2026-05-07T04:25:48.132Z",
      "violations": [],
      "last_passed_commit": "9b9a1213bb939b37f04da70a79069fdb0ab46110",
      "last_passed_date": "2026-05-04T11:33:35.886Z"
    },
    {
      "id": "multiply_reified_edges",
      "kind": "sparql",
      "label": "Multiply Reified Edges",
      "severity": "warning",
      "status": "pass",
      "ran_at": "2026-05-07T04:25:48.132Z",
      "violations": [],
      "last_passed_commit": "9b9a1213bb939b37f04da70a79069fdb0ab46110",
      "last_passed_date": "2026-05-04T11:33:35.886Z"
    }
  ]
}